[
  {
    "Id": 1,
    "IdUsuario": 1,
    "Usuario": {
      "Id": 1,
      "NombreUsuario": "admin",
      "Contrase\u00F1a": "admin",
      "Correo": "admin@example.com",
      "Estado": "Inactivo",
      "IdRol": 1,
      "Rol": {
        "Id": 1,
        "Nombre": "Administrador",
        "Usuarios": null,
        "Acciones": null,
        "Estado": "Activo"
      },
      "IdPerfil": 1,
      "Perfil": {
        "Id": 1,
        "Nombre": "Admin",
        "Apellido": "Usuario",
        "FechaNacimiento": "1980-01-01T00:00:00",
        "NumeroDocumento": null,
        "Telefono": null,
        "Usuarios": null,
        "Acciones": null,
        "StartMenuId": null,
        "Estado": "Activo"
      }
    },
    "FechaVenta": "2023-01-01T00:00:00",
    "Total": 100.00,
    "Estado": "Activo",
    "IdProducto": null,
    "Producto": null,
    "IdServicio": null,
    "Servicio": null,
    "Cantidad": 1,
    "Tipo": "Producto"
  },
  {
    "Id": 2,
    "IdUsuario": 1,
    "Usuario": {
      "Id": 1,
      "NombreUsuario": "admin",
      "Contrase\u00F1a": "admin",
      "Correo": "admin@example.com",
      "Estado": "Inactivo",
      "IdRol": 1,
      "Rol": {
        "Id": 1,
        "Nombre": "Administrador",
        "Usuarios": null,
        "Acciones": null,
        "Estado": "Activo"
      },
      "IdPerfil": 1,
      "Perfil": {
        "Id": 1,
        "Nombre": "Admin",
        "Apellido": "Usuario",
        "FechaNacimiento": "1980-01-01T00:00:00",
        "NumeroDocumento": null,
        "Telefono": null,
        "Usuarios": null,
        "Acciones": null,
        "StartMenuId": null,
        "Estado": "Activo"
      }
    },
    "FechaVenta": "2025-12-07T17:26:51.9685907-05:00",
    "Total": 35.50,
    "Estado": "Inactivo",
    "IdProducto": 2,
    "Producto": {
      "Id": 2,
      "Nombre": "Libro de Historia",
      "Descripcion": "Libro de historia mundial",
      "Precio": 35.50,
      "PrecioCompra": 20.75,
      "Stock": 30,
      "IdCategoria": 2,
      "Categoria": null,
      "FechaCreacion": "2023-02-20T00:00:00",
      "Estado": "Activo",
      "ImagenUrl": "/images/history-book.jpg"
    },
    "IdServicio": null,
    "Servicio": null,
    "Cantidad": 1,
    "Tipo": "Producto"
  },
  {
    "Id": 3,
    "IdUsuario": 1,
    "Usuario": {
      "Id": 1,
      "NombreUsuario": "admin",
      "Contrase\u00F1a": "admin",
      "Correo": "admin@example.com",
      "Estado": "Inactivo",
      "IdRol": 1,
      "Rol": {
        "Id": 1,
        "Nombre": "Administrador",
        "Usuarios": null,
        "Acciones": null,
        "Estado": "Activo"
      },
      "IdPerfil": 1,
      "Perfil": {
        "Id": 1,
        "Nombre": "Admin",
        "Apellido": "Usuario",
        "FechaNacimiento": "1980-01-01T00:00:00",
        "NumeroDocumento": null,
        "Telefono": null,
        "Usuarios": null,
        "Acciones": null,
        "StartMenuId": null,
        "Estado": "Activo"
      }
    },
    "FechaVenta": "2025-12-07T17:27:51.348035-05:00",
    "Total": 106.50,
    "Estado": "Activo",
    "IdProducto": 2,
    "Producto": {
      "Id": 2,
      "Nombre": "Libro de Historia",
      "Descripcion": "Libro de historia mundial",
      "Precio": 35.50,
      "PrecioCompra": 20.75,
      "Stock": 30,
      "IdCategoria": 2,
      "Categoria": null,
      "FechaCreacion": "2023-02-20T00:00:00",
      "Estado": "Activo",
      "ImagenUrl": "/images/history-book.jpg"
    },
    "IdServicio": null,
    "Servicio": null,
    "Cantidad": 3,
    "Tipo": "Producto"
  }
]