[
  {
    "Id": 1,
    "Title": "Inicio",
    "Url": "/Home/Index",
    "Icon": "fas fa-home",
    "Profiles": [ 1, 2 ],
    "Roles": [ 1 ],
    "ActionIds": [ 1, 2, 4, 3 ],
    "Estado": "Activo"
  },
  {
    "Id": 2,
    "Title": "Usuarios",
    "Url": "/Users/Index",
    "Icon": "fas fa-users",
    "Profiles": [ 1 ],
    "Roles": [ 1 ],
    "ActionIds": [ 1, 2, 3, 4 ],
    "Estado": "Activo"
  },
  {
    "Id": 3,
    "Title": "Libros",
    "Url": "/Books/Index",
    "Icon": "fas fa-book",
    "Profiles": [ 1, 2 ],
    "Roles": [ 1 ],
    "ActionIds": [ 1, 2, 3, 4 ],
    "Estado": "Activo"
  },
  {
    "Id": 4,
    "Title": "Colegios",
    "Url": "/Schools/Index",
    "Icon": "fas fa-school",
    "Profiles": [ 1, 2 ],
    "Roles": [ 1 ],
    "ActionIds": [ 1, 2, 3, 4, 5 ],
    "Estado": "Activo"
  },
  {
    "Id": 5,
    "Title": "Compras",
    "Url": "/Compras/Index",
    "Icon": "fas fa-shopping-cart",
    "Profiles": [ 1, 2 ],
    "Roles": [ 1 ],
    "ActionIds": [ 1, 2, 3, 4, 5 ],
    "Estado": "Activo"
  },
  {
    "Id": 6,
    "Title": "Pagos",
    "Url": "/Payments/Index",
    "Icon": "fas fa-credit-card",
    "Profiles": [ 1, 2 ],
    "Roles": [ 1 ],
    "ActionIds": [ 1, 2, 3, 4, 5 ],
    "Estado": "Activo"
  },
  {
    "Id": 7,
    "Title": "Ventas",
    "Url": "/Sales/Index",
    "Icon": "fas fa-chart-line",
    "Profiles": [ 1 ],
    "Roles": [ 1 ],
    "ActionIds": [ 1, 2, 4, 3 ],
    "Estado": "Activo"
  },
  {
    "Id": 8,
    "Title": "Solicitudes",
    "Url": "/Requests/Index",
    "Icon": "fas fa-clipboard-list",
    "Profiles": [ 1, 2 ],
    "Roles": [ 1 ],
    "ActionIds": [ 1, 2, 4, 3 ],
    "Estado": "Activo"
  },
  {
    "Id": 9,
    "Title": "Roles",
    "Url": "/Roles/Index",
    "Icon": "fas fa-user-tag",
    "Profiles": [ 1 ],
    "Roles": [ 1 ],
    "ActionIds": [ 1, 2, 4, 3 ],
    "Estado": "Activo"
  },
  {
    "Id": 10,
    "Title": "Perfiles",
    "Url": "/Profiles/Index",
    "Icon": "fas fa-id-card",
    "Profiles": [ 1 ],
    "Roles": [ 1 ],
    "ActionIds": [ 1, 2, 4, 3 ],
    "Estado": "Activo"
  },
  {
    "Id": 11,
    "Title": "Servicios",
    "Url": "/Services/Index",
    "Icon": "fas fa-cogs",
    "Profiles": [ 1 ],
    "Roles": [ 1 ],
    "ActionIds": [ 1, 2, 4, 3 ],
    "Estado": "Activo"
  },
  {
    "Id": 12,
    "Title": "Acciones",
    "Url": "/Actions/Index",
    "Icon": "fas fa-tasks",
    "Profiles": [ 1 ],
    "Roles": [ 1 ],
    "ActionIds": [ 1, 2, 4, 3 ],
    "Estado": "Activo"
  },
  {
    "Id": 13,
    "Title": "Opciones",
    "Url": "/Opcion/Index",
    "Icon": "fas fa-bars",
    "Profiles": [ 1 ],
    "Roles": [ 1 ],
    "ActionIds": [ 1, 2, 4, 3 ],
    "Estado": "Activo"
  },
  {
    "Id": 14,
    "Title": "Productos",
    "Url": "/Products/Index",
    "Icon": "fas fa-box",
    "Profiles": [ 1, 2 ],
    "Roles": [ 1 ],
    "ActionIds": [ 1, 2, 3, 4, 5 ],
    "Estado": "Activo"
  },
  {
    "Id": 15,
    "Title": "Categorías",
    "Url": "/Categories/Index",
    "Icon": "fas fa-tags",
    "Profiles": [ 1, 2 ],
    "Roles": [ 1 ],
    "ActionIds": [ 1, 2, 3, 4, 5 ],
    "Estado": "Activo"
  }
]
